{
  "db_name": "SQLite",
  "query": "\n            SELECT\n                ud.id as user_data_id,\n                ud.name as user_data_name,\n                joud.job_id as \"producer_job_id?\",\n                producer.name as \"producer_job_name?\",\n                jiud.job_id as \"consumer_job_id?\",\n                consumer.name as \"consumer_job_name?\",\n                ud.workflow_id as workflow_id\n            FROM user_data ud\n            LEFT JOIN job_output_user_data joud ON ud.id = joud.user_data_id\n            LEFT JOIN job producer ON joud.job_id = producer.id\n            LEFT JOIN job_input_user_data jiud ON ud.id = jiud.user_data_id\n            LEFT JOIN job consumer ON jiud.job_id = consumer.id\n            WHERE ud.workflow_id = ?\n                AND (joud.job_id IS NOT NULL OR jiud.job_id IS NOT NULL)\n            LIMIT ? OFFSET ?\n            ",
  "describe": {
    "columns": [
      {
        "name": "user_data_id",
        "ordinal": 0,
        "type_info": "Integer"
      },
      {
        "name": "user_data_name",
        "ordinal": 1,
        "type_info": "Text"
      },
      {
        "name": "producer_job_id?",
        "ordinal": 2,
        "type_info": "Integer"
      },
      {
        "name": "producer_job_name?",
        "ordinal": 3,
        "type_info": "Text"
      },
      {
        "name": "consumer_job_id?",
        "ordinal": 4,
        "type_info": "Integer"
      },
      {
        "name": "consumer_job_name?",
        "ordinal": 5,
        "type_info": "Text"
      },
      {
        "name": "workflow_id",
        "ordinal": 6,
        "type_info": "Integer"
      }
    ],
    "parameters": {
      "Right": 3
    },
    "nullable": [
      false,
      false,
      false,
      false,
      false,
      false,
      false
    ]
  },
  "hash": "ac8141c8bcfdcdcca29304cce0fbb7884b1d71829e7c460e4d90f8e003be0835"
}
